pcleaner/__init__.py
pcleaner/analytics.py
pcleaner/cli_utils.py
pcleaner/config.py
pcleaner/ctd_interface.py
pcleaner/denoiser.py
pcleaner/helpers.py
pcleaner/image_export.py
pcleaner/image_ops.py
pcleaner/inpainting.py
pcleaner/main.py
pcleaner/masker.py
pcleaner/memory_watcher.py
pcleaner/model_downloader.py
pcleaner/output_structures.py
pcleaner/preprocessor.py
pcleaner/profile_cli.py
pcleaner/structures.py
pcleaner/comic_text_detector/__init__.py
pcleaner/comic_text_detector/basemodel.py
pcleaner/comic_text_detector/inference.py
pcleaner/comic_text_detector/models/__init__.py
pcleaner/comic_text_detector/models/yolov5/__init__.py
pcleaner/comic_text_detector/models/yolov5/common.py
pcleaner/comic_text_detector/models/yolov5/yolo.py
pcleaner/comic_text_detector/utils/__init__.py
pcleaner/comic_text_detector/utils/db_utils.py
pcleaner/comic_text_detector/utils/export.py
pcleaner/comic_text_detector/utils/general.py
pcleaner/comic_text_detector/utils/imgproc_utils.py
pcleaner/comic_text_detector/utils/io_utils.py
pcleaner/comic_text_detector/utils/loss.py
pcleaner/comic_text_detector/utils/textblock.py
pcleaner/comic_text_detector/utils/textmask.py
pcleaner/comic_text_detector/utils/weight_init.py
pcleaner/comic_text_detector/utils/yolov5_utils.py
pcleaner/data/__init__.py
pcleaner/data/windows_explorer_integration_regedit.py
pcleaner/data/color_themes/__init__.py
pcleaner/data/custom_icons/__init__.py
pcleaner/data/theme_icons/__init__.py
pcleaner/data/translation_generated_files/__init__.py
pcleaner/ocr/__init__.py
pcleaner/ocr/ocr.py
pcleaner/ocr/ocr_mangaocr.py
pcleaner/ocr/ocr_tesseract.py
pcleaner/ocr/parsers.py
pcleaner/ocr/supported_languages.py
pcleaner_cli-2.11.9.dist-info/licenses/LICENSE
pcleaner_cli-2.11.9.dist-info/METADATA
pcleaner_cli-2.11.9.dist-info/WHEEL
pcleaner_cli-2.11.9.dist-info/entry_points.txt
pcleaner_cli-2.11.9.dist-info/top_level.txt
pcleaner_cli-2.11.9.dist-info/RECORD
