Metadata-Version: 2.4
Name: pcleaner-cli
Version: 2.11.9
Summary: An AI-powered tool to clean manga panels.
Home-page: https://github.com/VoxelCubes/PanelCleaner
Keywords: image processing,cleaning,text removal,manga,ai,machine learning
Classifier: Programming Language :: Python :: 3.10
Classifier: License :: OSI Approved :: GNU General Public License v3 or later (GPLv3+)
Classifier: Operating System :: POSIX :: Linux
Classifier: Operating System :: MacOS :: MacOS X
Classifier: Operating System :: Microsoft :: Windows
Classifier: Natural Language :: English
Requires-Python: >=3.10
License-File: LICENSE
Requires-Dist: opencv-python
Requires-Dist: transformers
Requires-Dist: manga_ocr
Requires-Dist: Pillow
Requires-Dist: torch
Requires-Dist: torchvision
Requires-Dist: tqdm
Requires-Dist: numpy
Requires-Dist: scipy
Requires-Dist: pyclipper
Requires-Dist: shapely
Requires-Dist: natsort
Requires-Dist: docopt-ng
Requires-Dist: ConfigUpdater
Requires-Dist: loguru
Requires-Dist: prettytable
Requires-Dist: colorama
Requires-Dist: requests
Requires-Dist: xdg
Requires-Dist: tifffile
Requires-Dist: PySide6>=6.7.0
Requires-Dist: attrs
Requires-Dist: psutil
Requires-Dist: dictdiffer
Requires-Dist: humanfriendly
Requires-Dist: simple_lama_inpainting
Requires-Dist: pytesseract
Requires-Dist: psd-tools
Requires-Dist: strenum; python_version < "3.11"
Requires-Dist: pywin32; platform_system == "Windows"
Requires-Dist: win10toast; platform_system == "Windows"
Requires-Dist: pyuac; platform_system == "Windows"
Provides-Extra: dbus
Requires-Dist: dbus-python; platform_system == "Linux" and extra == "dbus"
Dynamic: license-file
